{
    "complex_title": "Complex article",
    "complex_text": "<p>Collaboratively administrate empowered markets via plug-and-play networks. Dynamically procrastinate B2C users after installed base benefits. Dramatically visualize customer directed convergence without revolutionary ROI.<\/p><p>Efficiently unleash cross-media information without cross-media value. Quickly maximize timely deliverables for real-time schemas. Dramatically maintain clicks-and-mortar solutions without functional solutions.<\/p><p>Completely synergize resource sucking relationships via premier niche markets. Professionally cultivate one-to-one customer service with robust ideas. Dynamically innovate resource-leveling customer service for state of the art customer service.<\/p>",
    "address": {
        "streetName": "Broadway",
        "streetNumber": "721",
        "floor": 4,
        "addressType": {
            "typeName": "residential"
        }
    },
    "simple_title": "Simple article",
    "simple_text": "Collaboratively administrate empowered markets via plug-and-play networks. Dynamically procrastinate B2C users after installed base benefits. Dramatically visualize customer directed convergence without revolutionary ROI.",

    "layout": "main.hbs"
}